bahnapi/__init__.py
bahnapi/cli.py
bahnapi/client.py
bahnapi/config.py
bahnapi/departures.py
bahnapi/exceptions.py
bahnapi/parsers.py
bahnapi/stations.py
bahnapi/utils.py
bahnapi-0.1.0.dist-info/licenses/LICENSE
bahnapi-0.1.0.dist-info/METADATA
bahnapi-0.1.0.dist-info/WHEEL
bahnapi-0.1.0.dist-info/entry_points.txt
bahnapi-0.1.0.dist-info/top_level.txt
bahnapi-0.1.0.dist-info/RECORD
