Metadata-Version: 2.4
Name: bahnapi
Version: 0.1.0
Summary: Convenience wrapper for Deutsche Bahn Timetables API.
Author: Sebastian Speetzen
License: MIT License
Project-URL: Homepage, https://github.com/speetzial/bahnapi
Keywords: bahn,deutschebahn,train,timetable,api
Classifier: Development Status :: 3 - Alpha
Classifier: Intended Audience :: Developers
Classifier: License :: OSI Approved :: MIT License
Classifier: Programming Language :: Python
Classifier: Programming Language :: Python :: 3
Classifier: Programming Language :: Python :: 3.9
Classifier: Programming Language :: Python :: 3.10
Classifier: Programming Language :: Python :: 3.11
Classifier: Programming Language :: Python :: 3.12
Classifier: Topic :: Internet :: WWW/HTTP :: Dynamic Content
Classifier: Topic :: Software Development :: Libraries
Requires-Python: >=3.9
License-File: LICENSE
Requires-Dist: requests>=2.31.0
Provides-Extra: dev
Requires-Dist: python-dotenv>=1.0.0; extra == "dev"
Dynamic: license-file
